{
  "date": "2026-07-18",
  "commit_hash": "cdcfdec22d1ca43c736a60c4fd234c8acf5954f0bcd45fc39756221cade15d39",
  "payload": {
    "date": "2026-07-18",
    "board": [
      {
        "rank": 1,
        "symbol": "DEXE",
        "price": "36.452",
        "chg24hPct": "2.652773867",
        "mom30Pct": "151.2198484",
        "mom90Pct": "152.0013826",
        "trend": "UPTREND",
        "atr14Pct": "13.38827105",
        "distHighPct": "-26.25829422",
        "medVol30Usd": "5507498.765"
      },
      {
        "rank": 2,
        "symbol": "KAITO",
        "price": "0.8664",
        "chg24hPct": "2.097572472",
        "mom30Pct": "85.64388258",
        "mom90Pct": "96.41804579",
        "trend": "UPTREND",
        "atr14Pct": "9.669819264",
        "distHighPct": "-51.34497669",
        "medVol30Usd": "2298815.433"
      },
      {
        "rank": 3,
        "symbol": "XEC",
        "price": "8.24e-06",
        "chg24hPct": "30.58637084",
        "mom30Pct": "46.09929078",
        "mom90Pct": "15.24475524",
        "trend": "NEUTRAL",
        "atr14Pct": "10.1748918",
        "distHighPct": "-67.41795176",
        "medVol30Usd": "155644.0533"
      },
      {
        "rank": 4,
        "symbol": "LDO",
        "price": "0.3744",
        "chg24hPct": "2.659720318",
        "mom30Pct": "34.96755588",
        "mom90Pct": "-3.480278422",
        "trend": "NEUTRAL",
        "atr14Pct": "6.523053355",
        "distHighPct": "-77.002457",
        "medVol30Usd": "2540832.979"
      },
      {
        "rank": 5,
        "symbol": "SYRUP",
        "price": "0.1864",
        "chg24hPct": "1.249321021",
        "mom30Pct": "31.45275035",
        "mom90Pct": "-22.55920233",
        "trend": "NEUTRAL",
        "atr14Pct": "7.607584678",
        "distHighPct": "-72.58823529",
        "medVol30Usd": "1004100.354"
      },
      {
        "rank": 6,
        "symbol": "PYTH",
        "price": "0.0485",
        "chg24hPct": "-3.884264764",
        "mom30Pct": "24.35897436",
        "mom90Pct": "6.359649123",
        "trend": "NEUTRAL",
        "atr14Pct": "7.570926321",
        "distHighPct": "-80.6",
        "medVol30Usd": "2013534.816"
      },
      {
        "rank": 7,
        "symbol": "AAVE",
        "price": "89.99",
        "chg24hPct": "-1.315933765",
        "mom30Pct": "21.75618996",
        "mom90Pct": "-11.03311913",
        "trend": "NEUTRAL",
        "atr14Pct": "6.293441536",
        "distHighPct": "-76.68592451",
        "medVol30Usd": "16444743.11"
      },
      {
        "rank": 8,
        "symbol": "JST",
        "price": "0.09791",
        "chg24hPct": "0.4411161264",
        "mom30Pct": "16.92142345",
        "mom90Pct": "38.23238741",
        "trend": "UPTREND",
        "atr14Pct": "3.757653459",
        "distHighPct": "-6.413687631",
        "medVol30Usd": "3189559.246"
      },
      {
        "rank": 9,
        "symbol": "EIGEN",
        "price": "0.2357",
        "chg24hPct": "-4.458856911",
        "mom30Pct": "16.39506173",
        "mom90Pct": "31.09010011",
        "trend": "NEUTRAL",
        "atr14Pct": "9.363841735",
        "distHighPct": "-89.10309755",
        "medVol30Usd": "3575541.875"
      },
      {
        "rank": 10,
        "symbol": "ETHFI",
        "price": "0.44",
        "chg24hPct": "4.761904762",
        "mom30Pct": "14.88250653",
        "mom90Pct": "-7.172995781",
        "trend": "NEUTRAL",
        "atr14Pct": "8.192535286",
        "distHighPct": "-77.30789067",
        "medVol30Usd": "2619646.771"
      },
      {
        "rank": 11,
        "symbol": "ZEC",
        "price": "547.47",
        "chg24hPct": "4.534865959",
        "mom30Pct": "14.71827002",
        "mom90Pct": "69.41667956",
        "trend": "UPTREND",
        "atr14Pct": "8.081034151",
        "distHighPct": "-27.004",
        "medVol30Usd": "85739226.46"
      },
      {
        "rank": 12,
        "symbol": "UNI",
        "price": "3.64",
        "chg24hPct": "2.853913535",
        "mom30Pct": "12.79826464",
        "mom90Pct": "8.656716418",
        "trend": "NEUTRAL",
        "atr14Pct": "5.978543546",
        "distHighPct": "-70.40650407",
        "medVol30Usd": "12003239.71"
      },
      {
        "rank": 13,
        "symbol": "APE",
        "price": "0.1474",
        "chg24hPct": "-1.994680851",
        "mom30Pct": "11.41345427",
        "mom90Pct": "39.4512772",
        "trend": "UPTREND",
        "atr14Pct": "7.138559942",
        "distHighPct": "-80.97327998",
        "medVol30Usd": "1266418.951"
      },
      {
        "rank": 14,
        "symbol": "PUMP",
        "price": "0.001637",
        "chg24hPct": "-3.478773585",
        "mom30Pct": "10.90785908",
        "mom90Pct": "-12.73987207",
        "trend": "NEUTRAL",
        "atr14Pct": "8.551135195",
        "distHighPct": "-81.77060134",
        "medVol30Usd": "7939949.058"
      },
      {
        "rank": 15,
        "symbol": "RAY",
        "price": "0.6739",
        "chg24hPct": "0.2827380952",
        "mom30Pct": "9.222042139",
        "mom90Pct": "1.951588502",
        "trend": "NEUTRAL",
        "atr14Pct": "5.482277103",
        "distHighPct": "-83.63128492",
        "medVol30Usd": "573649.683"
      },
      {
        "rank": 16,
        "symbol": "GNO",
        "price": "114.11",
        "chg24hPct": "-2.135506003",
        "mom30Pct": "8.541805384",
        "mom90Pct": "-6.643213614",
        "trend": "NEUTRAL",
        "atr14Pct": "7.485127839",
        "distHighPct": "-45.66190476",
        "medVol30Usd": "101346.5628"
      },
      {
        "rank": 17,
        "symbol": "POL",
        "price": "0.08303",
        "chg24hPct": "1.802354095",
        "mom30Pct": "7.929286364",
        "mom90Pct": "-7.332589286",
        "trend": "NEUTRAL",
        "atr14Pct": "3.941513372",
        "distHighPct": "-71.98717949",
        "medVol30Usd": "2788229.495"
      },
      {
        "rank": 18,
        "symbol": "ARB",
        "price": "0.0906",
        "chg24hPct": "1.797752809",
        "mom30Pct": "5.717619603",
        "mom90Pct": "-29.87616099",
        "trend": "NEUTRAL",
        "atr14Pct": "6.699626772",
        "distHighPct": "-85.49471662",
        "medVol30Usd": "4185342.897"
      },
      {
        "rank": 19,
        "symbol": "PENDLE",
        "price": "1.54",
        "chg24hPct": "-0.7092198582",
        "mom30Pct": "5.551747772",
        "mom90Pct": "13.40206186",
        "trend": "NEUTRAL",
        "atr14Pct": "6.950688893",
        "distHighPct": "-75.48941588",
        "medVol30Usd": "2561522.394"
      },
      {
        "rank": 20,
        "symbol": "SUN",
        "price": "0.01821",
        "chg24hPct": "0.7190265487",
        "mom30Pct": "5.381944444",
        "mom90Pct": "-1.032608696",
        "trend": "NEUTRAL",
        "atr14Pct": "2.144871574",
        "distHighPct": "-58.61363636",
        "medVol30Usd": "677884.7054"
      },
      {
        "rank": 21,
        "symbol": "ETH",
        "price": "1841.93",
        "chg24hPct": "-1.221637681",
        "mom30Pct": "5.217068434",
        "mom90Pct": "-21.63067157",
        "trend": "NEUTRAL",
        "atr14Pct": "4.178181396",
        "distHighPct": "-62.84019061",
        "medVol30Usd": "444518348.5"
      },
      {
        "rank": 22,
        "symbol": "SKY",
        "price": "0.0597",
        "chg24hPct": "-2.419091206",
        "mom30Pct": "4.736842105",
        "mom90Pct": "-21.74596933",
        "trend": "NEUTRAL",
        "atr14Pct": "6.00438021",
        "distHighPct": "-37.15789474",
        "medVol30Usd": "1275064.614"
      },
      {
        "rank": 23,
        "symbol": "DCR",
        "price": "12.56",
        "chg24hPct": "-5.135951662",
        "mom30Pct": "4.492512479",
        "mom90Pct": "-38.37095191",
        "trend": "NEUTRAL",
        "atr14Pct": "8.703262016",
        "distHighPct": "-82.05714286",
        "medVol30Usd": "198660.1487"
      },
      {
        "rank": 24,
        "symbol": "SOL",
        "price": "75.04",
        "chg24hPct": "-0.3717472119",
        "mom30Pct": "4.149895906",
        "mom90Pct": "-12.90622098",
        "trend": "NEUTRAL",
        "atr14Pct": "4.519714264",
        "distHighPct": "-70.39958976",
        "medVol30Usd": "152013291.1"
      },
      {
        "rank": 25,
        "symbol": "BCH",
        "price": "219.7",
        "chg24hPct": "-0.9914375845",
        "mom30Pct": "3.388235294",
        "mom90Pct": "-50.46223224",
        "trend": "DOWNTREND",
        "atr14Pct": "5.765332103",
        "distHighPct": "-67.18936679",
        "medVol30Usd": "7492322.569"
      },
      {
        "rank": 26,
        "symbol": "VIRTUAL",
        "price": "0.6242",
        "chg24hPct": "-0.03203074952",
        "mom30Pct": "2.901417738",
        "mom90Pct": "-11.24697853",
        "trend": "NEUTRAL",
        "atr14Pct": "6.989645536",
        "distHighPct": "-68.27445997",
        "medVol30Usd": "2517522.588"
      },
      {
        "rank": 27,
        "symbol": "RUNE",
        "price": "0.43",
        "chg24hPct": "1.895734597",
        "mom30Pct": "2.870813397",
        "mom90Pct": "1.41509434",
        "trend": "NEUTRAL",
        "atr14Pct": "4.612352011",
        "distHighPct": "-75.4985755",
        "medVol30Usd": "994922.5001"
      },
      {
        "rank": 28,
        "symbol": "CAKE",
        "price": "1.411",
        "chg24hPct": "1.437814522",
        "mom30Pct": "2.394775036",
        "mom90Pct": "-8.554763448",
        "trend": "NEUTRAL",
        "atr14Pct": "4.00948004",
        "distHighPct": "-69.34607864",
        "medVol30Usd": "1584265.547"
      },
      {
        "rank": 29,
        "symbol": "ONDO",
        "price": "0.3731",
        "chg24hPct": "2.528167079",
        "mom30Pct": "2.219178082",
        "mom90Pct": "44.5563735",
        "trend": "UPTREND",
        "atr14Pct": "6.164100411",
        "distHighPct": "-68.09747755",
        "medVol30Usd": "6441393.782"
      },
      {
        "rank": 30,
        "symbol": "JUP",
        "price": "0.194",
        "chg24hPct": "-1.272264631",
        "mom30Pct": "2.212855638",
        "mom90Pct": "8.379888268",
        "trend": "NEUTRAL",
        "atr14Pct": "8.144844204",
        "distHighPct": "-71.88405797",
        "medVol30Usd": "2435796.123"
      },
      {
        "rank": 31,
        "symbol": "LINK",
        "price": "8.254",
        "chg24hPct": "-1.043040403",
        "mom30Pct": "2.001977261",
        "mom90Pct": "-11.05603448",
        "trend": "NEUTRAL",
        "atr14Pct": "4.277584725",
        "distHighPct": "-70.38392537",
        "medVol30Usd": "14569186.02"
      },
      {
        "rank": 32,
        "symbol": "BTT",
        "price": "0.002677",
        "chg24hPct": "5.852115461",
        "mom30Pct": "1.55538695",
        "mom90Pct": "-25.05599104",
        "trend": "DOWNTREND",
        "atr14Pct": "7.971818444",
        "distHighPct": "-80.28370257",
        "medVol30Usd": "26249387.51"
      },
      {
        "rank": 33,
        "symbol": "LTC",
        "price": "45.17",
        "chg24hPct": "0.5117935024",
        "mom30Pct": "0.5565449688",
        "mom90Pct": "-18.83198562",
        "trend": "NEUTRAL",
        "atr14Pct": "3.590813367",
        "distHighPct": "-66.78432238",
        "medVol30Usd": "12786636.2"
      },
      {
        "rank": 34,
        "symbol": "TRX",
        "price": "0.3227",
        "chg24hPct": "-0.1855861429",
        "mom30Pct": "0.2796768179",
        "mom90Pct": "-2.063732929",
        "trend": "NEUTRAL",
        "atr14Pct": "1.362731831",
        "distHighPct": "-14.51655629",
        "medVol30Usd": "34161923.06"
      },
      {
        "rank": 35,
        "symbol": "BFUSD",
        "price": "0.9992",
        "chg24hPct": "0.01000900811",
        "mom30Pct": "-0.0500150045",
        "mom90Pct": "-0.0200120072",
        "trend": "DOWNTREND",
        "atr14Pct": "0.03712286211",
        "distHighPct": "-7.481481481",
        "medVol30Usd": "1330622.046"
      },
      {
        "rank": 36,
        "symbol": "ADA",
        "price": "0.1667",
        "chg24hPct": "3.604723431",
        "mom30Pct": "-0.1198322349",
        "mom90Pct": "-33.0790847",
        "trend": "DOWNTREND",
        "atr14Pct": "5.959887476",
        "distHighPct": "-83.64563916",
        "medVol30Usd": "20184865.72"
      },
      {
        "rank": 37,
        "symbol": "BTC",
        "price": "63931.67",
        "chg24hPct": "0.1589686387",
        "mom30Pct": "-0.8955749085",
        "mom90Pct": "-15.53681669",
        "trend": "NEUTRAL",
        "atr14Pct": "3.008069375",
        "distHighPct": "-49.34084197",
        "medVol30Usd": "1139321995"
      },
      {
        "rank": 38,
        "symbol": "MORPHO",
        "price": "1.966",
        "chg24hPct": "-5.298651252",
        "mom30Pct": "-0.9571788413",
        "mom90Pct": "2.12987013",
        "trend": "UPTREND",
        "atr14Pct": "7.796723825",
        "distHighPct": "-18.79388682",
        "medVol30Usd": "1983651.919"
      },
      {
        "rank": 39,
        "symbol": "AVAX",
        "price": "6.591",
        "chg24hPct": "1.182069389",
        "mom30Pct": "-2.58646172",
        "mom90Pct": "-29.35691318",
        "trend": "DOWNTREND",
        "atr14Pct": "4.945448799",
        "distHighPct": "-81.77267699",
        "medVol30Usd": "13446507.61"
      },
      {
        "rank": 40,
        "symbol": "TIA",
        "price": "0.3785",
        "chg24hPct": "-4.851684263",
        "mom30Pct": "-3.468502933",
        "mom90Pct": "-3.517716034",
        "trend": "NEUTRAL",
        "atr14Pct": "7.839450996",
        "distHighPct": "-83.44269466",
        "medVol30Usd": "4077180.273"
      },
      {
        "rank": 41,
        "symbol": "COMP",
        "price": "17.02",
        "chg24hPct": "-0.7001166861",
        "mom30Pct": "-3.514739229",
        "mom90Pct": "-33.25490196",
        "trend": "DOWNTREND",
        "atr14Pct": "4.689402249",
        "distHighPct": "-70.15082427",
        "medVol30Usd": "427409.2484"
      },
      {
        "rank": 42,
        "symbol": "SUI",
        "price": "0.74",
        "chg24hPct": "0.1353179973",
        "mom30Pct": "-3.557930405",
        "mom90Pct": "-22.63460533",
        "trend": "DOWNTREND",
        "atr14Pct": "5.139091309",
        "distHighPct": "-83.3468359",
        "medVol30Usd": "19287559.34"
      },
      {
        "rank": 43,
        "symbol": "ETC",
        "price": "7.04",
        "chg24hPct": "1.44092219",
        "mom30Pct": "-3.825136612",
        "mom90Pct": "-17.17647059",
        "trend": "DOWNTREND",
        "atr14Pct": "3.836673476",
        "distHighPct": "-72.84998072",
        "medVol30Usd": "1472931.577"
      },
      {
        "rank": 44,
        "symbol": "CRV",
        "price": "0.2184",
        "chg24hPct": "-0.7723761926",
        "mom30Pct": "-4.042179262",
        "mom90Pct": "-4.628820961",
        "trend": "NEUTRAL",
        "atr14Pct": "6.366204761",
        "distHighPct": "-81.21451918",
        "medVol30Usd": "1760850.271"
      },
      {
        "rank": 45,
        "symbol": "FIL",
        "price": "0.765",
        "chg24hPct": "-0.6493506494",
        "mom30Pct": "-4.135338346",
        "mom90Pct": "-18.78980892",
        "trend": "DOWNTREND",
        "atr14Pct": "5.510348582",
        "distHighPct": "-80.74502895",
        "medVol30Usd": "4721824.053"
      },
      {
        "rank": 46,
        "symbol": "AXS",
        "price": "0.944",
        "chg24hPct": "-3.476482618",
        "mom30Pct": "-4.646464646",
        "mom90Pct": "-15.93944791",
        "trend": "DOWNTREND",
        "atr14Pct": "5.584889893",
        "distHighPct": "-68.50183517",
        "medVol30Usd": "1202792.036"
      },
      {
        "rank": 47,
        "symbol": "DASH",
        "price": "34.3",
        "chg24hPct": "2.817745803",
        "mom30Pct": "-5.431486077",
        "mom90Pct": "-0.6660874602",
        "trend": "DOWNTREND",
        "atr14Pct": "6.020394229",
        "distHighPct": "-77.13333333",
        "medVol30Usd": "3832152.65"
      },
      {
        "rank": 48,
        "symbol": "INJ",
        "price": "5.148",
        "chg24hPct": "5.94772587",
        "mom30Pct": "-5.489260143",
        "mom90Pct": "60.77451593",
        "trend": "NEUTRAL",
        "atr14Pct": "6.757990266",
        "distHighPct": "-68.89425982",
        "medVol30Usd": "4811255.719"
      },
      {
        "rank": 49,
        "symbol": "BNB",
        "price": "568.09",
        "chg24hPct": "-0.7616385711",
        "mom30Pct": "-5.574854977",
        "mom90Pct": "-9.812668678",
        "trend": "DOWNTREND",
        "atr14Pct": "3.024829268",
        "distHighPct": "-58.68766862",
        "medVol30Usd": "58523538.97"
      },
      {
        "rank": 50,
        "symbol": "VET",
        "price": "0.004721",
        "chg24hPct": "-0.27460921",
        "mom30Pct": "-6.403647898",
        "mom90Pct": "-33.20599887",
        "trend": "DOWNTREND",
        "atr14Pct": "4.817400504",
        "distHighPct": "-84.02368866",
        "medVol30Usd": "542291.2348"
      },
      {
        "rank": 51,
        "symbol": "PEPE",
        "price": "2.74e-06",
        "chg24hPct": "0.7352941176",
        "mom30Pct": "-7.118644068",
        "mom90Pct": "-27.32095491",
        "trend": "DOWNTREND",
        "atr14Pct": "6.238106225",
        "distHighPct": "-81.42372881",
        "medVol30Usd": "14463750.86"
      },
      {
        "rank": 52,
        "symbol": "WIF",
        "price": "0.1553",
        "chg24hPct": "2.779616148",
        "mom30Pct": "-7.228195938",
        "mom90Pct": "-23.11881188",
        "trend": "DOWNTREND",
        "atr14Pct": "6.264443345",
        "distHighPct": "-88.27924528",
        "medVol30Usd": "1851052.849"
      },
      {
        "rank": 53,
        "symbol": "APT",
        "price": "0.622",
        "chg24hPct": "1.800327332",
        "mom30Pct": "-7.44047619",
        "mom90Pct": "-33.54700855",
        "trend": "DOWNTREND",
        "atr14Pct": "5.630214334",
        "distHighPct": "-89.01254195",
        "medVol30Usd": "3288257.774"
      },
      {
        "rank": 54,
        "symbol": "QNT",
        "price": "65.13",
        "chg24hPct": "2.196767613",
        "mom30Pct": "-7.551454933",
        "mom90Pct": "-12.02215318",
        "trend": "DOWNTREND",
        "atr14Pct": "4.450439504",
        "distHighPct": "-51.96194129",
        "medVol30Usd": "597825.8645"
      },
      {
        "rank": 55,
        "symbol": "XRP",
        "price": "1.089",
        "chg24hPct": "0.1747769294",
        "mom30Pct": "-8.240647118",
        "mom90Pct": "-23.96844237",
        "trend": "DOWNTREND",
        "atr14Pct": "3.869623456",
        "distHighPct": "-70.25159123",
        "medVol30Usd": "80172151.81"
      },
      {
        "rank": 56,
        "symbol": "JASMY",
        "price": "0.00451",
        "chg24hPct": "2.5",
        "mom30Pct": "-8.333333333",
        "mom90Pct": "-19.60784314",
        "trend": "DOWNTREND",
        "atr14Pct": "5.804298353",
        "distHighPct": "-78.32772705",
        "medVol30Usd": "562607.4628"
      },
      {
        "rank": 57,
        "symbol": "ICP",
        "price": "2.144",
        "chg24hPct": "0.9891662741",
        "mom30Pct": "-8.49338455",
        "mom90Pct": "-13.86098835",
        "trend": "DOWNTREND",
        "atr14Pct": "5.460582216",
        "distHighPct": "-78.23129252",
        "medVol30Usd": "3778362.932"
      },
      {
        "rank": 58,
        "symbol": "XTZ",
        "price": "0.2222",
        "chg24hPct": "0.6796556411",
        "mom30Pct": "-8.634868421",
        "mom90Pct": "-39.12328767",
        "trend": "DOWNTREND",
        "atr14Pct": "6.028506178",
        "distHighPct": "-81.92614283",
        "medVol30Usd": "396454.6102"
      },
      {
        "rank": 59,
        "symbol": "NEXO",
        "price": "0.749",
        "chg24hPct": "0.1336898396",
        "mom30Pct": "-8.658536585",
        "mom90Pct": "-17.1460177",
        "trend": "DOWNTREND",
        "atr14Pct": "4.406646338",
        "distHighPct": "-46.42346209",
        "medVol30Usd": "336315.1891"
      },
      {
        "rank": 60,
        "symbol": "WLFI",
        "price": "0.0571",
        "chg24hPct": "-0.8680555556",
        "mom30Pct": "-9.076433121",
        "mom90Pct": "-27.72151899",
        "trend": "DOWNTREND",
        "atr14Pct": "4.095402664",
        "distHighPct": "-88.05439331",
        "medVol30Usd": "3619221.755"
      },
      {
        "rank": 61,
        "symbol": "THETA",
        "price": "0.145",
        "chg24hPct": "-1.56143924",
        "mom30Pct": "-10.27227723",
        "mom90Pct": "-33.48623853",
        "trend": "DOWNTREND",
        "atr14Pct": "6.156532344",
        "distHighPct": "-85.67193676",
        "medVol30Usd": "437901.2216"
      },
      {
        "rank": 62,
        "symbol": "CFX",
        "price": "0.04609",
        "chg24hPct": "3.109619687",
        "mom30Pct": "-10.47008547",
        "mom90Pct": "-23.69205298",
        "trend": "NEUTRAL",
        "atr14Pct": "4.989832349",
        "distHighPct": "-83.53340479",
        "medVol30Usd": "635168.7736"
      },
      {
        "rank": 63,
        "symbol": "NEAR",
        "price": "1.927",
        "chg24hPct": "-1.933842239",
        "mom30Pct": "-11.68652612",
        "mom90Pct": "43.48473567",
        "trend": "NEUTRAL",
        "atr14Pct": "7.215554209",
        "distHighPct": "-42.33991622",
        "medVol30Usd": "31231785.28"
      },
      {
        "rank": 64,
        "symbol": "OP",
        "price": "0.096",
        "chg24hPct": "-2.73556231",
        "mom30Pct": "-11.76470588",
        "mom90Pct": "-23.74900715",
        "trend": "DOWNTREND",
        "atr14Pct": "6.375853494",
        "distHighPct": "-89.14027149",
        "medVol30Usd": "2231517.936"
      },
      {
        "rank": 65,
        "symbol": "KAIA",
        "price": "0.033",
        "chg24hPct": "-2.077151335",
        "mom30Pct": "-12",
        "mom90Pct": "-32.92682927",
        "trend": "DOWNTREND",
        "atr14Pct": "4.625202959",
        "distHighPct": "-81.73768677",
        "medVol30Usd": "555151.3347"
      },
      {
        "rank": 66,
        "symbol": "GRT",
        "price": "0.01711",
        "chg24hPct": "-0.523255814",
        "mom30Pct": "-12.30138391",
        "mom90Pct": "-31.25753315",
        "trend": "DOWNTREND",
        "atr14Pct": "4.850472155",
        "distHighPct": "-85.81260365",
        "medVol30Usd": "628406.0901"
      },
      {
        "rank": 67,
        "symbol": "RENDER",
        "price": "1.478",
        "chg24hPct": "0.135501355",
        "mom30Pct": "-12.80235988",
        "mom90Pct": "-16.73239437",
        "trend": "DOWNTREND",
        "atr14Pct": "5.258855118",
        "distHighPct": "-68.65988126",
        "medVol30Usd": "2930724.138"
      },
      {
        "rank": 68,
        "symbol": "ASTER",
        "price": "0.624",
        "chg24hPct": "0.9708737864",
        "mom30Pct": "-12.9707113",
        "mom90Pct": "-7.004470939",
        "trend": "DOWNTREND",
        "atr14Pct": "3.492757071",
        "distHighPct": "-79.2",
        "medVol30Usd": "4991460.399"
      },
      {
        "rank": 69,
        "symbol": "STX",
        "price": "0.1649",
        "chg24hPct": "-1.434548715",
        "mom30Pct": "-13.3473463",
        "mom90Pct": "-28.58380251",
        "trend": "DOWNTREND",
        "atr14Pct": "5.372387454",
        "distHighPct": "-82.0174482",
        "medVol30Usd": "500630.6247"
      },
      {
        "rank": 70,
        "symbol": "2Z",
        "price": "0.06501",
        "chg24hPct": "-2.387387387",
        "mom30Pct": "-13.59649123",
        "mom90Pct": "-26.84820524",
        "trend": "DOWNTREND",
        "atr14Pct": "7.476561706",
        "distHighPct": "-94.92109375",
        "medVol30Usd": "415268.033"
      },
      {
        "rank": 71,
        "symbol": "PENGU",
        "price": "0.005934",
        "chg24hPct": "-1.673570837",
        "mom30Pct": "-13.73746184",
        "mom90Pct": "-18.26446281",
        "trend": "DOWNTREND",
        "atr14Pct": "6.869944362",
        "distHighPct": "-87.26828012",
        "medVol30Usd": "4842721.122"
      },
      {
        "rank": 72,
        "symbol": "ENA",
        "price": "0.082",
        "chg24hPct": "-0.3645200486",
        "mom30Pct": "-13.77497371",
        "mom90Pct": "-31.60967473",
        "trend": "DOWNTREND",
        "atr14Pct": "7.090390752",
        "distHighPct": "-90.60387304",
        "medVol30Usd": "13161351.53"
      },
      {
        "rank": 73,
        "symbol": "TWT",
        "price": "0.3466",
        "chg24hPct": "-0.630733945",
        "mom30Pct": "-14.14416646",
        "mom90Pct": "-15.42215715",
        "trend": "DOWNTREND",
        "atr14Pct": "5.082471289",
        "distHighPct": "-79.99076319",
        "medVol30Usd": "289716.6975"
      },
      {
        "rank": 74,
        "symbol": "ENS",
        "price": "4.57",
        "chg24hPct": "7.783018868",
        "mom30Pct": "-14.41947566",
        "mom90Pct": "-23.57859532",
        "trend": "DOWNTREND",
        "atr14Pct": "5.38923066",
        "distHighPct": "-85.81185967",
        "medVol30Usd": "567116.0529"
      },
      {
        "rank": 75,
        "symbol": "NEO",
        "price": "1.947",
        "chg24hPct": "0.3091190108",
        "mom30Pct": "-14.53028973",
        "mom90Pct": "-32.67634855",
        "trend": "DOWNTREND",
        "atr14Pct": "4.041748271",
        "distHighPct": "-77.2546729",
        "medVol30Usd": "287511.0157"
      },
      {
        "rank": 76,
        "symbol": "SEI",
        "price": "0.04691",
        "chg24hPct": "-0.3399192692",
        "mom30Pct": "-14.86388385",
        "mom90Pct": "-16.1722659",
        "trend": "DOWNTREND",
        "atr14Pct": "5.745175316",
        "distHighPct": "-87.45386467",
        "medVol30Usd": "2485932.231"
      },
      {
        "rank": 77,
        "symbol": "LIT",
        "price": "0.694",
        "chg24hPct": "-7.343124166",
        "mom30Pct": "-15.05507956",
        "mom90Pct": "-4.011065007",
        "trend": "NEUTRAL",
        "atr14Pct": "27.90930478",
        "distHighPct": "-64.17139907",
        "medVol30Usd": "3190023.218"
      },
      {
        "rank": 78,
        "symbol": "DOT",
        "price": "0.849",
        "chg24hPct": "-1.164144354",
        "mom30Pct": "-15.43824701",
        "mom90Pct": "-33.25471698",
        "trend": "DOWNTREND",
        "atr14Pct": "5.096506359",
        "distHighPct": "-82.60958624",
        "medVol30Usd": "5066577.573"
      },
      {
        "rank": 79,
        "symbol": "DOGE",
        "price": "0.07256",
        "chg24hPct": "0.2763957988",
        "mom30Pct": "-15.55917607",
        "mom90Pct": "-23.45184091",
        "trend": "DOWNTREND",
        "atr14Pct": "4.255961249",
        "distHighPct": "-76.35249642",
        "medVol30Usd": "32307663.31"
      },
      {
        "rank": 80,
        "symbol": "SHIB",
        "price": "4.15e-06",
        "chg24hPct": "0.9732360097",
        "mom30Pct": "-16.16161616",
        "mom90Pct": "-31.51815182",
        "trend": "DOWNTREND",
        "atr14Pct": "4.489531096",
        "distHighPct": "-74.01377583",
        "medVol30Usd": "2589781.21"
      },
      {
        "rank": 81,
        "symbol": "ALGO",
        "price": "0.0828",
        "chg24hPct": "0.4854368932",
        "mom30Pct": "-16.53225806",
        "mom90Pct": "-22.18045113",
        "trend": "DOWNTREND",
        "atr14Pct": "4.9790173",
        "distHighPct": "-75.35714286",
        "medVol30Usd": "1962656.889"
      },
      {
        "rank": 82,
        "symbol": "FLOKI",
        "price": "2.157e-05",
        "chg24hPct": "-0.09263547939",
        "mom30Pct": "-17.00654098",
        "mom90Pct": "-29.76229241",
        "trend": "DOWNTREND",
        "atr14Pct": "5.100897035",
        "distHighPct": "-86.32819928",
        "medVol30Usd": "1045013.084"
      },
      {
        "rank": 83,
        "symbol": "FF",
        "price": "0.06323",
        "chg24hPct": "-1.908160099",
        "mom30Pct": "-17.2382199",
        "mom90Pct": "-12.39955666",
        "trend": "DOWNTREND",
        "atr14Pct": "7.082473406",
        "distHighPct": "-89.09827586",
        "medVol30Usd": "1209975.319"
      },
      {
        "rank": 84,
        "symbol": "XLM",
        "price": "0.1855",
        "chg24hPct": "0.161987041",
        "mom30Pct": "-17.7748227",
        "mom90Pct": "8.861502347",
        "trend": "NEUTRAL",
        "atr14Pct": "6.239490121",
        "distHighPct": "-64.36803688",
        "medVol30Usd": "17351030.99"
      },
      {
        "rank": 85,
        "symbol": "TRUMP",
        "price": "1.554",
        "chg24hPct": "0.5825242718",
        "mom30Pct": "-18.89352818",
        "mom90Pct": "-46.02292463",
        "trend": "DOWNTREND",
        "atr14Pct": "5.799248944",
        "distHighPct": "-86.96308725",
        "medVol30Usd": "5923101.326"
      },
      {
        "rank": 86,
        "symbol": "HBAR",
        "price": "0.0659",
        "chg24hPct": "-1.021327726",
        "mom30Pct": "-18.94218942",
        "mom90Pct": "-25.77157017",
        "trend": "DOWNTREND",
        "atr14Pct": "4.453344956",
        "distHighPct": "-78.39344262",
        "medVol30Usd": "5462215.833"
      },
      {
        "rank": 87,
        "symbol": "STRK",
        "price": "0.0278",
        "chg24hPct": "-1.418439716",
        "mom30Pct": "-19.18604651",
        "mom90Pct": "-21.46892655",
        "trend": "DOWNTREND",
        "atr14Pct": "6.376872108",
        "distHighPct": "-90.05366726",
        "medVol30Usd": "1166639.958"
      },
      {
        "rank": 88,
        "symbol": "LUNC",
        "price": "5.814e-05",
        "chg24hPct": "-0.5643919959",
        "mom30Pct": "-19.42904656",
        "mom90Pct": "36.47887324",
        "trend": "NEUTRAL",
        "atr14Pct": "5.798168607",
        "distHighPct": "-52.73170732",
        "medVol30Usd": "1844164.599"
      },
      {
        "rank": 89,
        "symbol": "JTO",
        "price": "0.5632",
        "chg24hPct": "-1.036724653",
        "mom30Pct": "-19.48534668",
        "mom90Pct": "76.27543036",
        "trend": "NEUTRAL",
        "atr14Pct": "12.70864837",
        "distHighPct": "-75.61904762",
        "medVol30Usd": "6001787.457"
      },
      {
        "rank": 90,
        "symbol": "FET",
        "price": "0.1595",
        "chg24hPct": "0.9493670886",
        "mom30Pct": "-20.21010505",
        "mom90Pct": "-25.88289963",
        "trend": "DOWNTREND",
        "atr14Pct": "5.980556302",
        "distHighPct": "-81.99774266",
        "medVol30Usd": "7749002.687"
      },
      {
        "rank": 91,
        "symbol": "ATOM",
        "price": "1.511",
        "chg24hPct": "-0.06613756614",
        "mom30Pct": "-20.47368421",
        "mom90Pct": "-15.25518789",
        "trend": "DOWNTREND",
        "atr14Pct": "4.144912489",
        "distHighPct": "-71.58171901",
        "medVol30Usd": "1611390.986"
      },
      {
        "rank": 92,
        "symbol": "TAO",
        "price": "194.7",
        "chg24hPct": "1.777313121",
        "mom30Pct": "-20.98214286",
        "mom90Pct": "-19.97533909",
        "trend": "DOWNTREND",
        "atr14Pct": "6.220219448",
        "distHighPct": "-63.90433815",
        "medVol30Usd": "16862825.69"
      },
      {
        "rank": 93,
        "symbol": "ZRO",
        "price": "0.78",
        "chg24hPct": "-4.05904059",
        "mom30Pct": "-23.37917485",
        "mom90Pct": "-56.17977528",
        "trend": "DOWNTREND",
        "atr14Pct": "8.983662207",
        "distHighPct": "-69.9884571",
        "medVol30Usd": "2847439.767"
      },
      {
        "rank": 94,
        "symbol": "IOTA",
        "price": "0.0359",
        "chg24hPct": "1.126760563",
        "mom30Pct": "-24.26160338",
        "mom90Pct": "-36.68430335",
        "trend": "DOWNTREND",
        "atr14Pct": "7.595251451",
        "distHighPct": "-86.02024922",
        "medVol30Usd": "683012.4632"
      },
      {
        "rank": 95,
        "symbol": "XPL",
        "price": "0.08529",
        "chg24hPct": "-1.318986463",
        "mom30Pct": "-24.32120674",
        "mom90Pct": "-21.8956044",
        "trend": "DOWNTREND",
        "atr14Pct": "10.76595075",
        "distHighPct": "-94.96219728",
        "medVol30Usd": "12813603.31"
      },
      {
        "rank": 96,
        "symbol": "XMR",
        "price": "112.5",
        "chg24hPct": "-7.71123872",
        "mom30Pct": "-28.20676452",
        "mom90Pct": "-29.15617128",
        "trend": "DOWNTREND",
        "atr14Pct": "9.186868789",
        "distHighPct": "-37.742114",
        "medVol30Usd": "13893470.9"
      },
      {
        "rank": 97,
        "symbol": "CHZ",
        "price": "0.01599",
        "chg24hPct": "-4.480286738",
        "mom30Pct": "-33.76139188",
        "mom90Pct": "-60.4697157",
        "trend": "DOWNTREND",
        "atr14Pct": "7.493098269",
        "distHighPct": "-75.14765309",
        "medVol30Usd": "2478355.732"
      },
      {
        "rank": 98,
        "symbol": "BONK",
        "price": "3.07e-06",
        "chg24hPct": "-11.01449275",
        "mom30Pct": "-33.8362069",
        "mom90Pct": "-49.17218543",
        "trend": "DOWNTREND",
        "atr14Pct": "10.5197504",
        "distHighPct": "-91.92105263",
        "medVol30Usd": "2053466.929"
      },
      {
        "rank": 99,
        "symbol": "KITE",
        "price": "0.1132",
        "chg24hPct": "-6.907894737",
        "mom30Pct": "-39.36797001",
        "mom90Pct": "-20.11291461",
        "trend": "DOWNTREND",
        "atr14Pct": "10.61681198",
        "distHighPct": "-64.98608104",
        "medVol30Usd": "3412169.515"
      },
      {
        "rank": 100,
        "symbol": "WLD",
        "price": "0.3886",
        "chg24hPct": "0.07725985063",
        "mom30Pct": "-41.00500987",
        "mom90Pct": "47.53227031",
        "trend": "NEUTRAL",
        "atr14Pct": "10.22526649",
        "distHighPct": "-82.42424242",
        "medVol30Usd": "29723550.34"
      }
    ],
    "dial": {
      "verdict": "RISK-OFF",
      "btcClose": "63931.67",
      "btcMa20": "62700.329",
      "btcMa50": "63772.261",
      "stackTrue": false,
      "breadthPct": "35"
    },
    "nonce": "45030d07c066afa1a95fafd5938a405362229a0dc7c2923700ee377e76871e9b"
  }
}